bitmex_client/__init__.py
bitmex_client/api_client.py
bitmex_client/configuration.py
bitmex_client/rest.py
bitmex_client/apis/__init__.py
bitmex_client/apis/announcement_api.py
bitmex_client/apis/api_key_api.py
bitmex_client/apis/chat_api.py
bitmex_client/apis/execution_api.py
bitmex_client/apis/funding_api.py
bitmex_client/apis/instrument_api.py
bitmex_client/apis/insurance_api.py
bitmex_client/apis/leaderboard_api.py
bitmex_client/apis/liquidation_api.py
bitmex_client/apis/notification_api.py
bitmex_client/apis/order_api.py
bitmex_client/apis/order_book_api.py
bitmex_client/apis/position_api.py
bitmex_client/apis/quote_api.py
bitmex_client/apis/schema_api.py
bitmex_client/apis/settlement_api.py
bitmex_client/apis/stats_api.py
bitmex_client/apis/trade_api.py
bitmex_client/apis/user_api.py
bitmex_client/models/__init__.py
bitmex_client/models/access_token.py
bitmex_client/models/affiliate.py
bitmex_client/models/announcement.py
bitmex_client/models/api_key.py
bitmex_client/models/chat.py
bitmex_client/models/chat_channel.py
bitmex_client/models/connected_users.py
bitmex_client/models/error.py
bitmex_client/models/error_error.py
bitmex_client/models/execution.py
bitmex_client/models/funding.py
bitmex_client/models/index_composite.py
bitmex_client/models/inline_response_200.py
bitmex_client/models/instrument.py
bitmex_client/models/instrument_interval.py
bitmex_client/models/insurance.py
bitmex_client/models/leaderboard.py
bitmex_client/models/liquidation.py
bitmex_client/models/margin.py
bitmex_client/models/notification.py
bitmex_client/models/order.py
bitmex_client/models/order_book.py
bitmex_client/models/order_book_l2.py
bitmex_client/models/position.py
bitmex_client/models/quote.py
bitmex_client/models/settlement.py
bitmex_client/models/stats.py
bitmex_client/models/stats_history.py
bitmex_client/models/trade.py
bitmex_client/models/trade_bin.py
bitmex_client/models/transaction.py
bitmex_client-1.0.19.dist-info/DESCRIPTION.rst
bitmex_client-1.0.19.dist-info/METADATA
bitmex_client-1.0.19.dist-info/RECORD
bitmex_client-1.0.19.dist-info/WHEEL
bitmex_client-1.0.19.dist-info/metadata.json
bitmex_client-1.0.19.dist-info/top_level.txt
bitmex_client-1.0.19.dist-info/zip-safe
