Metadata-Version: 1.1
Name: bitmex-client
Version: 1.0.19
Summary: Bitmex websocket API
Home-page: https://github.com/joliveros/bitmex-websocket
Author: José Oliveros
Author-email: jose.oliveros.1983@gmail.com
License: MIT License
Keywords: bitmex websocket bot cryptocurrency
Platform: UNKNOWN
Classifier: Development Status :: 3 - Alpha
Classifier: Intended Audience :: Developers
Classifier: Topic :: Software Development
Classifier: License :: OSI Approved :: MIT License
Classifier: Programming Language :: Python :: 3.4
Classifier: Programming Language :: Python :: 3.5
Classifier: Programming Language :: Python :: 3.6
